MANIFEST.in
README.md
setup.py
imgs/code_md.png
imgs/code_show.png
imgs/code_view.png
imgs/code_view_find.png
imgs/index.png
imgs/md_edit.png
pythonnote/__init__.py
pythonnote/config.py
pythonnote.egg-info/PKG-INFO
pythonnote.egg-info/SOURCES.txt
pythonnote.egg-info/dependency_links.txt
pythonnote.egg-info/requires.txt
pythonnote.egg-info/top_level.txt
pythonnote/logs/count_day.txt
pythonnote/logs/count_view_code.txt
pythonnote/pythonnote_md/Study_001_Hello.md
pythonnote/pythonnotes/Study_001_Hello.py
pythonnote/web/Items.py
pythonnote/web/code_util.py
pythonnote/web/main.py
pythonnote/web/server.py
pythonnote/web/simple_server.py
pythonnote/web/utils.py
pythonnote/web/Skulpt/index.html
pythonnote/web/Skulpt/js/index.js
pythonnote/web/Skulpt/js/jquery.min.js
pythonnote/web/Skulpt/js/skulpt-stdlib.js
pythonnote/web/Skulpt/js/skulpt.min.js
pythonnote/web/codemirror_python/.DS_Store
pythonnote/web/codemirror_python/Skulpt.js
pythonnote/web/codemirror_python/axios.js
pythonnote/web/codemirror_python/index.html
pythonnote/web/codemirror_python/index.js
pythonnote/web/codemirror_python/leetcode.css
pythonnote/web/codemirror_python/python-hint.js
pythonnote/web/codemirror_python/codemirror/AUTHORS
pythonnote/web/codemirror_python/codemirror/CHANGELOG.md
pythonnote/web/codemirror_python/codemirror/CONTRIBUTING.md
pythonnote/web/codemirror_python/codemirror/LICENSE
pythonnote/web/codemirror_python/codemirror/README.md
pythonnote/web/codemirror_python/codemirror/package.json
pythonnote/web/codemirror_python/codemirror/rollup.config.js
pythonnote/web/codemirror_python/codemirror/addon/comment/comment.js
pythonnote/web/codemirror_python/codemirror/addon/comment/continuecomment.js
pythonnote/web/codemirror_python/codemirror/addon/dialog/dialog.css
pythonnote/web/codemirror_python/codemirror/addon/dialog/dialog.js
pythonnote/web/codemirror_python/codemirror/addon/display/autorefresh.js
pythonnote/web/codemirror_python/codemirror/addon/display/fullscreen.css
pythonnote/web/codemirror_python/codemirror/addon/display/fullscreen.js
pythonnote/web/codemirror_python/codemirror/addon/display/panel.js
