Metadata-Version: 2.1
Name: pythonnote
Version: 1.0.1
Summary: Easy study Python on web
Home-page: https://github.com/425776024/pythonnote
Author: Jiang.XinFa
Author-email: 425776024@qq.com
License: MIT Licence
Keywords: pythonnote,python
Platform: any
